sparkpl/__init__.py
sparkpl/converter.py
sparkpl-2.0.1.dist-info/METADATA
sparkpl-2.0.1.dist-info/WHEEL
sparkpl-2.0.1.dist-info/RECORD
