Metadata-Version: 2.4
Name: sparkpl
Version: 2.0.1
Summary: A utility package for converting between PySpark and Polars DataFrames
Project-URL: Homepage, https://github.com/Boadzie/sparkpl
Project-URL: Bug Tracker, https://github.com/Boadzie/sparkpl/issues
Author-email: Daniel Boadzie <boadziedaniel43@gmail.com>
Classifier: License :: OSI Approved :: MIT License
Classifier: Operating System :: OS Independent
Classifier: Programming Language :: Python :: 3
Classifier: Topic :: Scientific/Engineering :: Information Analysis
Requires-Python: >=3.11
Requires-Dist: loguru>=0.7.3
Requires-Dist: polars>=1.31.0
Requires-Dist: pyarrow>=20.0.0
Requires-Dist: pyspark>=4.0.0
